fast_template_python/__init__.py
fast_template_python/__main__.py
fast_template_python/conf/__init__.py-tpl
fast_template_python/conf/base_template/.gitignore-tpl
fast_template_python/conf/base_template/Makefile-tpl
fast_template_python/conf/base_template/Readme.md-tpl
fast_template_python/conf/base_template/__init__.py-tpl
fast_template_python/conf/base_template/make_db_migrations.py-tpl
fast_template_python/conf/base_template/pyproject.toml-tpl
fast_template_python/conf/base_template/requirements.txt-tpl
fast_template_python/conf/database_template/__init__.py-tpl
fast_template_python/conf/database_template/db_handlers/__init__.py-tpl
fast_template_python/conf/database_template/db_handlers/auth_db_handler.py-tpl
fast_template_python/conf/database_template/orms/__init__.py-tpl
fast_template_python/conf/database_template/orms/auth_orm.py-tpl
fast_template_python/conf/job_manager_template/email/mailer.py-tpl
fast_template_python/conf/job_manager_template/job_runner.py-tpl
fast_template_python/conf/root_template/__init__.py-tpl
fast_template_python/conf/root_template/app.py-tpl
fast_template_python/conf/root_template/app_routers.py-tpl
fast_template_python/conf/root_template/arq_worker.py-tpl
fast_template_python/conf/root_template/constants.py-tpl
fast_template_python/conf/root_template/database.py-tpl
fast_template_python/conf/root_template/logging.py-tpl
fast_template_python/conf/root_template/redis_manager.py-tpl
fast_template_python/conf/root_template/settings.py-tpl
fast_template_python/conf/root_template/templates/auth/info_email_template.html-tpl
fast_template_python/conf/root_template/utils/abstract_base.py-tpl
fast_template_python/conf/root_template/utils/base_models_abstract.py-tpl
fast_template_python/conf/routers_template/__init__.py-tpl
fast_template_python/conf/routers_template/auth_router.py-tpl
fast_template_python/conf/routers_template/miscellenenous_router.py-tpl
fast_template_python/conf/schemas_template/__init__.py-tpl
fast_template_python-0.1.4.dist-info/METADATA
fast_template_python-0.1.4.dist-info/WHEEL
fast_template_python-0.1.4.dist-info/entry_points.txt
fast_template_python-0.1.4.dist-info/RECORD
