Metadata-Version: 2.1
Name: fast-template-python
Version: 0.1.4
Summary: Easily generate a template for your Fastapi applications, complete with JWT authentication and Google sign-in
Keywords: fastapi,template,python,fast-template-python
Author: Peter Akande
Author-email: akandepeter86@gmail.com
Requires-Python: >=3.8,<4.0
Classifier: Programming Language :: Python :: 3
Classifier: Programming Language :: Python :: 3.8
Classifier: Programming Language :: Python :: 3.9
Classifier: Programming Language :: Python :: 3.10
Classifier: Programming Language :: Python :: 3.11
Classifier: Programming Language :: Python :: 3.12
Requires-Dist: typer (>=0.12.5,<0.13.0)
